normie/__init__.py
normie/compat/__init__.py
normie/compat/excel.py
normie_impl.cp313-win_amd64.pyd
normie-0.4.0.dist-info/entry_points.txt
normie-0.4.0.dist-info/LICENSE
normie-0.4.0.dist-info/METADATA
normie-0.4.0.dist-info/WHEEL
normie-0.4.0.dist-info/RECORD
