Metadata-Version: 2.3
Name: normie
Version: 0.4.0
Summary: Accurate and efficient normal distribution statistics.
Home-page: https://github.com/jwg4/normie
License: MIT
Author: Jack Grahl
Author-email: jack.grahl@gmail.com
Maintainer: Jack Grahl
Maintainer-email: jack.grahl@gmail.com
Requires-Python: >=3.7
Classifier: License :: OSI Approved :: MIT License
Classifier: Programming Language :: Python :: 3
Classifier: Programming Language :: Python :: 3.7
Classifier: Programming Language :: Python :: 3.8
Classifier: Programming Language :: Python :: 3.9
Classifier: Programming Language :: Python :: 3.10
Classifier: Programming Language :: Python :: 3.11
Classifier: Programming Language :: Python :: 3.12
Classifier: Programming Language :: Python :: 3.13
Requires-Dist: setuptools (>=56.0.0,<57.0.0)
Project-URL: Repository, https://github.com/jwg4/normie
